<keymap version="1" name="GNOME copy" parent="Default for GNOME">
  <action id="CloseContent">
    <keyboard-shortcut first-keystroke="alt w" />
  </action>
  <action id="CodeCompletion" />
  <action id="EditorScrollToCenter" />
  <action id="FileChooser.NewFolder">
    <keyboard-shortcut first-keystroke="alt insert" />
  </action>
  <action id="FileChooser.TogglePathShowing" />
  <action id="GotoChangedFile" />
  <action id="GotoClass" />
  <action id="HtmlTableCellNavigateDown">
    <keyboard-shortcut first-keystroke="ctrl n" />
  </action>
  <action id="HtmlTableCellNavigateUp">
    <keyboard-shortcut first-keystroke="ctrl p" />
  </action>
  <action id="ParameterInfo" />
  <action id="Vcs.ShowMessageHistory">
    <keyboard-shortcut first-keystroke="ctrl e" />
  </action>
  <action id="VimPluginToggle">
    <keyboard-shortcut first-keystroke="ctrl m" />
  </action>
  <action id="org.intellij.plugins.markdown.ui.actions.editorLayout.CyclicSplitLayoutChangeAction" />
</keymap>